odoo10_addon_l10n_it_base_location_geonames_import-10.0.1.0.0-py2.7-nspkg.pth
odoo/addons/l10n_it_base_location_geonames_import/__manifest__.py
odoo/addons/l10n_it_base_location_geonames_import/geonames_import.py
odoo/addons/l10n_it_base_location_geonames_import/__init__.py
odoo/addons/l10n_it_base_location_geonames_import/i18n/nb_NO.po
odoo/addons/l10n_it_base_location_geonames_import/i18n/it.po
odoo/addons/l10n_it_base_location_geonames_import/test/import.yml
odoo10_addon_l10n_it_base_location_geonames_import-10.0.1.0.0.dist-info/top_level.txt
odoo10_addon_l10n_it_base_location_geonames_import-10.0.1.0.0.dist-info/WHEEL
odoo10_addon_l10n_it_base_location_geonames_import-10.0.1.0.0.dist-info/RECORD
odoo10_addon_l10n_it_base_location_geonames_import-10.0.1.0.0.dist-info/metadata.json
odoo10_addon_l10n_it_base_location_geonames_import-10.0.1.0.0.dist-info/DESCRIPTION.rst
odoo10_addon_l10n_it_base_location_geonames_import-10.0.1.0.0.dist-info/METADATA
odoo10_addon_l10n_it_base_location_geonames_import-10.0.1.0.0.dist-info/namespace_packages.txt
