Metadata-Version: 2.0
Name: odoo10-addon-l10n-it-base-location-geonames-import
Version: 10.0.1.0.0
Summary: Import base_location entries (provinces) from Geonames
Home-page: http://www.agilebg.com
Author: Agile Business Group,Odoo Community Association (OCA)
Author-email: support@odoo-community.org
License: AGPL-3
Platform: UNKNOWN
Requires-Dist: odoo (<10.1dev,>=10.0)
Requires-Dist: odoo10-addon-base-location-geonames-import
Classifier: Programming Language :: Python :: 2.7
Classifier: Framework :: Odoo
Classifier: License :: OSI Approved :: GNU Affero General Public License v3
